random_neural_net_models/__init__.py
random_neural_net_models/autoencoder_fastai2022.py
random_neural_net_models/backprop_rumelhart.py
random_neural_net_models/convolution_lecun1990.py
random_neural_net_models/data.py
random_neural_net_models/learner.py
random_neural_net_models/losses.py
random_neural_net_models/perceptron.py
random_neural_net_models/resnet.py
random_neural_net_models/search.py
random_neural_net_models/tabular.py
random_neural_net_models/tabular_vae.py
random_neural_net_models/telemetry.py
random_neural_net_models/text.py
random_neural_net_models/tokenization.py
random_neural_net_models/transformer.py
random_neural_net_models/unet.py
random_neural_net_models/unet_with_noise.py
random_neural_net_models/utils.py
random_neural_net_models/variational_autoencoder_fastai2022.py
random_neural_net_models/mingpt/__init__.py
random_neural_net_models/mingpt/adder.py
random_neural_net_models/mingpt/char.py
random_neural_net_models/mingpt/configs.py
random_neural_net_models/mingpt/model.py
random_neural_net_models/mingpt/sorter.py
random_neural_net_models/mingpt/trainer.py
random_neural_net_models/mingpt/utils.py
random_neural_net_models-0.3.2.dist-info/METADATA
random_neural_net_models-0.3.2.dist-info/WHEEL
random_neural_net_models-0.3.2.dist-info/licenses/LICENSE
random_neural_net_models-0.3.2.dist-info/RECORD
