Metadata-Version: 2.4
Name: random-neural-net-models
Version: 0.3.2
Summary: Implementation of a random selection of artificial neural net based models.
Project-URL: Homepage, https://github.com/eschmidt42/random-neural-net-models
Project-URL: Repository, https://github.com/eschmidt42/random-neural-net-models
Project-URL: Issues, https://github.com/eschmidt42/random-neural-net-models/issues
Author-email: eschmidt42 <11818904+eschmidt42@users.noreply.github.com>
License: BSD 3-Clause License
License-File: LICENSE
Keywords: deep-learning,machine-learning,neural-networks
Classifier: Development Status :: 3 - Alpha
Classifier: Programming Language :: Python :: 3.10
Classifier: Programming Language :: Python :: 3.11
Classifier: Programming Language :: Python :: 3.12
Classifier: Programming Language :: Python :: 3.13
Requires-Python: >=3.10
Requires-Dist: diffusers[torch]
Requires-Dist: einops
Requires-Dist: matplotlib
Requires-Dist: numpy
Requires-Dist: pandas
Requires-Dist: pydantic
Requires-Dist: regex
Requires-Dist: rich
Requires-Dist: scikit-learn
Requires-Dist: seaborn
Requires-Dist: tabulate
Requires-Dist: tensordict
Requires-Dist: tifffile
Requires-Dist: torch
Requires-Dist: torchvision
Requires-Dist: tqdm
Requires-Dist: transformers
Requires-Dist: wandb
